{
  "main": {
    "id": "56775289354f0b24",
    "type": "split",
    "children": [
      {
        "id": "0bc29a2021c30567",
        "type": "tabs",
        "children": [
          {
            "id": "8d65f3222f8fd0b3",
            "type": "leaf",
            "state": {
              "type": "markdown",
              "state": {
                "file": "Google.md",
                "mode": "source",
                "source": false
              },
              "icon": "lucide-file",
              "title": "Google"
            }
          }
        ]
      }
    ],
    "direction": "vertical"
  },
  "left": {
    "id": "308f7c7c034f1700",
    "type": "mobile-drawer",
    "children": [
      {
        "id": "e47639dea82f087e",
        "type": "leaf",
        "state": {
          "type": "file-explorer",
          "state": {
            "sortOrder": "alphabetical"
          },
          "icon": "lucide-folder-closed",
          "title": "Files"
        }
      },
      {
        "id": "d84c8b15c59bf44a",
        "type": "leaf",
        "state": {
          "type": "search",
          "state": {
            "query": "",
            "matchingCase": false,
            "explainSearch": false,
            "collapseAll": false,
            "extraContext": false,
            "sortOrder": "alphabetical"
          },
          "icon": "lucide-search",
          "title": "Search"
        }
      },
      {
        "id": "b11dab917c323035",
        "type": "leaf",
        "state": {
          "type": "tag",
          "state": {
            "sortOrder": "frequency",
            "useHierarchy": true
          },
          "icon": "lucide-tags",
          "title": "Tags"
        }
      },
      {
        "id": "ff96c359220b6991",
        "type": "leaf",
        "state": {
          "type": "bookmarks",
          "state": {},
          "icon": "lucide-bookmark",
          "title": "Bookmarks"
        }
      }
    ],
    "currentTab": 0
  },
  "right": {
    "id": "8b2367588fcb0eb4",
    "type": "mobile-drawer",
    "children": [
      {
        "id": "2c4e1f5310a8778a",
        "type": "leaf",
        "state": {
          "type": "backlink",
          "state": {
            "file": "Short Term 10 days.md",
            "collapseAll": false,
            "extraContext": false,
            "sortOrder": "alphabetical",
            "showSearch": false,
            "searchQuery": "",
            "backlinkCollapsed": false,
            "unlinkedCollapsed": true
          },
          "icon": "links-coming-in",
          "title": "Backlinks"
        }
      },
      {
        "id": "f5a35f34c6deef51",
        "type": "leaf",
        "state": {
          "type": "outgoing-link",
          "state": {
            "file": "Short Term 10 days.md",
            "linksCollapsed": false,
            "unlinkedCollapsed": true
          },
          "icon": "links-going-out",
          "title": "Outgoing links"
        }
      },
      {
        "id": "3d459642784b534d",
        "type": "leaf",
        "state": {
          "type": "outline",
          "state": {
            "file": "Short Term 10 days.md"
          },
          "icon": "lucide-list",
          "title": "Outline"
        }
      },
      {
        "id": "a1fe43a107bd11be",
        "type": "leaf",
        "state": {
          "type": "git-view",
          "state": {},
          "icon": "git-pull-request",
          "title": "Source Control"
        }
      }
    ],
    "currentTab": 3
  },
  "left-ribbon": {
    "hiddenItems": {
      "templater-obsidian:Templater": false,
      "switcher:Open quick switcher": false,
      "graph:Open graph view": false,
      "canvas:Create new canvas": false,
      "daily-notes:Open today's daily note": false,
      "templates:Insert template": false,
      "command-palette:Open command palette": false,
      "obsidian-git:Open Git source control": false
    }
  },
  "active": "8d65f3222f8fd0b3",
  "lastOpenFiles": [
    "2024-09-24.md",
    "Google.md",
    "Daily Tasks.md",
    "December.md",
    "Diwali.md",
    "Pasted image 20250223235902.png",
    "TODO.md",
    "Weekly.md",
    "Welcome.md",
    "Short Term 10 days.md",
    "Microservices/gRPC.md",
    "templater/Project Template.md",
    "Microservices/_Project Template.md",
    "templater",
    "Microservices",
    "TOTD.md",
    "2024-09-06.md",
    "To do.md"
  ]
}